{
  "id": "07-07-derived-asset-image-workflow-dedupe",
  "name": "07-07-derived-asset-image-workflow-dedupe",
  "title": "Derived asset image workflow dedupe and generation logic",
  "description": "Fix duplicate derived-asset image workflow nodes and align character derived asset image generation with Toonflow-style three-view output.",
  "status": "completed",
  "dev_type": null,
  "scope": null,
  "package": null,
  "priority": "P1",
  "creator": "xinzhuzi",
  "assignee": "xinzhuzi",
  "createdAt": "2026-07-07",
  "completedAt": "2026-07-10",
  "branch": null,
  "base_branch": "main",
  "worktree_path": null,
  "commit": null,
  "pr_url": null,
  "subtasks": [],
  "children": [],
  "parent": "07-07-toonflow-image-workflow-deep-audit",
  "relatedFiles": [],
  "notes": "Fresh checks passed: focused Vitest, typecheck, lint, full Vitest, build:mac, packaged smoke, overwrite install, app.asar hash match, installed smoke, video:daojie:chapter001 with storyboard-image reuse gate, real Daojie visible workflow runner. Character derived fallback image inspected as 1600x900 four-panel reference sheet; scene/prop inspected as unchanged 1280x720 single-image cards.",
  "meta": {}
}